open_source_init/__init__.py
open_source_init/cli.py
open_source_init/credentials.py
open_source_init/github_init.py
open_source_init/pypi_init.py
open_source_init/travis_init.py
open_source_init-0.1.4.dist-info/top_level.txt
open_source_init-0.1.4.dist-info/entry_points.txt
open_source_init-0.1.4.dist-info/METADATA
open_source_init-0.1.4.dist-info/DESCRIPTION.rst
open_source_init-0.1.4.dist-info/metadata.json
open_source_init-0.1.4.dist-info/WHEEL
open_source_init-0.1.4.dist-info/RECORD
