Metadata-Version: 2.0
Name: open-source-init
Version: 0.1.4
Summary: A tool to automatically create a github repo, integrate travis, code coverage, read the docs, and everything else necessary for OSS development
Home-page: https://github.com/timmartin19/open_source_init
Author: Tim Martin
Author-email: tim@timmartin.me
License: MIT license
Keywords: open_source_init
Platform: UNKNOWN
Classifier: Development Status :: 2 - Pre-Alpha
Classifier: Intended Audience :: Developers
Classifier: License :: OSI Approved :: MIT License
Classifier: Natural Language :: English
Classifier: Programming Language :: Python :: 2
Classifier: Programming Language :: Python :: 2.6
Classifier: Programming Language :: Python :: 2.7
Classifier: Programming Language :: Python :: 3
Classifier: Programming Language :: Python :: 3.3
Classifier: Programming Language :: Python :: 3.4
Classifier: Programming Language :: Python :: 3.5
Requires-Dist: Click (>=6.0)
Requires-Dist: PyGithub
Requires-Dist: PyYaml
Requires-Dist: TravisPy
Requires-Dist: cryptography
Requires-Dist: gitpython
Requires-Dist: keyring
Requires-Dist: py-env-config
Requires-Dist: requests
Requires-Dist: retrying
